url_backoff_registry/__init__.py
url_backoff_registry/registry.py
url_backoff_registry-1.1.1.dist-info/licenses/LICENSE
url_backoff_registry-1.1.1.dist-info/METADATA
url_backoff_registry-1.1.1.dist-info/WHEEL
url_backoff_registry-1.1.1.dist-info/top_level.txt
url_backoff_registry-1.1.1.dist-info/RECORD
