Metadata-Version: 2.4
Name: url-backoff-registry
Version: 1.1.1
Summary: In-memory URL backoff registry with sliding window thresholds.
Author-email: Lars de Ridder <lars@deridder.me>
License: MIT
Project-URL: Homepage, https://github.com/larsderidder/url-backoff-registry
Project-URL: Repository, https://github.com/larsderidder/url-backoff-registry
Keywords: backoff,retry,url,rate-limit,circuit-breaker
Classifier: Development Status :: 4 - Beta
Classifier: Intended Audience :: Developers
Classifier: License :: OSI Approved :: MIT License
Classifier: Programming Language :: Python :: 3
Classifier: Programming Language :: Python :: 3.8
Classifier: Programming Language :: Python :: 3.9
Classifier: Programming Language :: Python :: 3.10
Classifier: Programming Language :: Python :: 3.11
Classifier: Programming Language :: Python :: 3.12
Classifier: Typing :: Typed
Requires-Python: >=3.8
License-File: LICENSE
Requires-Dist: typing_extensions>=4.0; python_version < "3.10"
Provides-Extra: dev
Requires-Dist: pytest; extra == "dev"
Dynamic: license-file
